prediction/__init__.py
prediction/urls.py
prediction/wsgi.py
prediction/__pycache__/__init__.cpython-36.pyc
prediction/__pycache__/urls.cpython-36.pyc
prediction/__pycache__/wsgi.cpython-36.pyc
prediction/settings/__init__.py
prediction/settings/base.py
prediction/settings/development.py
prediction/settings/production.py
prediction/settings/testing.py
prediction/settings/__pycache__/__init__.cpython-36.pyc
prediction/settings/__pycache__/base.cpython-36.pyc
prediction/settings/__pycache__/development.cpython-36.pyc
prediction/settings/__pycache__/production.cpython-36.pyc
prediction/settings/__pycache__/testing.cpython-36.pyc
prediction/test_a/test_b/test.txt
prediction-0.0.3.dist-info/DESCRIPTION.rst
prediction-0.0.3.dist-info/METADATA
prediction-0.0.3.dist-info/RECORD
prediction-0.0.3.dist-info/WHEEL
prediction-0.0.3.dist-info/metadata.json
prediction-0.0.3.dist-info/top_level.txt
scoring/__init__.py
scoring/admin.py
scoring/apps.py
scoring/models.py
scoring/views.py
scoring/__pycache__/__init__.cpython-36.pyc
scoring/__pycache__/admin.cpython-36.pyc
scoring/__pycache__/models.cpython-36.pyc
scoring/api/__init__.py
scoring/api/hello_world.py
scoring/api/__pycache__/__init__.cpython-36.pyc
scoring/api/__pycache__/hello_world.cpython-36.pyc
scoring/fixtures/test.txt
scoring/migrations/__init__.py
scoring/migrations/__pycache__/__init__.cpython-36.pyc
scoring/tests/__init__.py
scoring/tests/test_hello_world.py
scoring/tests/__pycache__/__init__.cpython-36.pyc
scoring/tests/__pycache__/test_hello_world.cpython-36.pyc
scoring/utils/__init__.py
scoring/utils/context_managers.py
scoring/utils/decorators.py
scoring/utils/__pycache__/__init__.cpython-36.pyc
scoring/utils/__pycache__/decorators.cpython-36.pyc
