Metadata-Version: 2.0
Name: prediction
Version: 0.0.3
Summary: Django skeleton project
Home-page: http://github.com/omritoptix/django-skeleton
Author: Omri Dagan
Author-email: omritoptix@gmail.com
License: MIT
Platform: UNKNOWN
Requires-Dist: dj-database-url (==0.4.2)
Requires-Dist: Django (==2.0)
Requires-Dist: django-cors-headers (==2.1.0)
Requires-Dist: django-filter (==1.1.0)
Requires-Dist: django-rest-framework (==0.1.0)
Requires-Dist: djangorestframework (==3.7.7)
Requires-Dist: djangorestframework-filters (==0.10.2)
Requires-Dist: pytz (==2017.3)
Requires-Dist: uWSGI (==2.0.15)
